prio_encoder_16_4.vhd
library ieee;
use ieee.std_logic_1164.all;
use ieee.numeric_std.all;

entity prio_encoder_16_4 is
  port (
    input : in std_logic_vector(15 downto 0);
    index : out std_logic_vector(3 downto 0);
    valid : out std_logic
  );
end entity;

architecture arch of prio_encoder_16_4 is
begin
  prio_encode: process(input)
  begin
    if input(15) = '1' then
      index <= "1111";
      valid <= '1';
    elsif input(14) = '1' then
      index <= "1110";
      valid <= '1';
    elsif input(13) = '1' then
      index <= "1101";
      valid <= '1';
    elsif input(12) = '1' then
      index <= "1100";
      valid <= '1';
    elsif input(11) = '1' then
      index <= "1011";
      valid <= '1';
    elsif input(10) = '1' then
      index <= "1010";
      valid <= '1';
    elsif input(9) = '1' then
      index <= "1001";
      valid <= '1';
    elsif input(8) = '1' then
      index <= "1000";
      valid <= '1';
    elsif input(7) = '1' then
      index <= "0111";
      valid <= '1';
    elsif input(6) = '1' then
      index <= "0110";
      valid <= '1';
    elsif input(5) = '1' then
      index <= "0101";
      valid <= '1';
    elsif input(4) = '1' then
      index <= "0100";
      valid <= '1';
    elsif input(3) = '1' then
      index <= "0011";
      valid <= '1';
    elsif input(2) = '1' then
      index <= "0010";
      valid <= '1';
    elsif input(1) = '1' then
      index <= "0001";
      valid <= '1';
    elsif input(0) = '1' then
      index <= "0000";
      valid <= '1';
    else
      valid <= '0';
    end if;

  end process;
end architecture;

prio_encoder_64_6.vhd
library ieee;
use ieee.std_logic_1164.all;
use ieee.numeric_std.all;

entity prio_encoder_64_6 is
  port (
    input : in std_logic_vector(63 downto 0);
    index : out std_logic_vector(5 downto 0);
    valid : out std_logic
  );
end entity;

architecture arch of prio_encoder_64_6 is
  component prio_encoder_16_4 is
  port (
    input : in std_logic_vector(15 downto 0);
    index : out std_logic_vector(3 downto 0);
    valid : out std_logic
  );
  end component;


  signal index0, index1, index2, index3: std_logic_vector(3 downto 0);
  signal valid0, valid1, valid2, valid3: std_logic;
begin
  p_e_0: prio_encoder_16_4 
  port map (
    input => input(15 downto 0),
    index => index0,
    valid => valid0);
  p_e_1: prio_encoder_16_4 
  port map (
    input => input(31 downto 16),
    index => index1,
    valid => valid1);
  p_e_2: prio_encoder_16_4 
  port map (
    input => input(47 downto 32),
    index => index2,
    valid => valid2);
  p_e_3: prio_encoder_16_4 
  port map (
    input => input(63 downto 48),
    index => index3,
    valid => valid3);


  out_mux: process(index0, index1, index2, index3, valid0, valid1, valid2, valid3)
  begin
    if valid3 = '1' and valid3 = '1' then
      index <= "11" & index3;
      valid <= '1';
    elsif valid2 = '1' and valid2 = '1' then
      index <= "10" & index2;
      valid <= '1';
    elsif valid1 = '1' and valid1 = '1' then
      index <= "01" & index1;
      valid <= '1';
    elsif valid0 = '1' and valid0 = '1' then
      index <= "00" & index0;
      valid <= '1';
    else
      valid <= '0';
    end if;
  end process;


end architecture;

prio_tb.vhd
library ieee;

use ieee.std_logic_1164.all;
use ieee.numeric_std.all;

--  A testbench has no ports.
entity prio_tb is
end prio_tb;

architecture behav of prio_tb is
  --  Declaration of the component that will be instantiated.
  component prio_encoder_64_6 is
  port (
    input : in std_logic_vector(63 downto 0);
    index : out std_logic_vector(5 downto 0);
    valid : out std_logic
  );
  end component;

  --  Specifies which entity is bound with the component.
  for prio_0: prio_encoder_64_6 use entity work.prio_encoder_64_6;
  signal input : std_logic_vector(63 downto 0);
  signal index : std_logic_vector(5 downto 0);
  signal valid : std_logic;


  
begin
  --  Component instantiation.
  prio_0: prio_encoder_64_6 port map (input => input, index => index, valid => valid);

  --  This process does the real job.
  process
    type pattern_type is record
      --  The inputs of the adder.
      input : std_logic_vector(63 downto 0);
      --  The expected outputs of the adder.
      index : std_logic_vector(5 downto 0);
      valid : std_logic;
    end record;
    --  The patterns to apply.
    type pattern_array is array (natural range <>) of pattern_type;
    constant patterns : pattern_array :=
      ((x"000000000000" & "1000000000100000", "001111", '1'),
       (x"000000000000" & "0000000000000001", "000000", '1'),
       (x"000000000000" & "0010000000000000", "001101", '1'),
       (x"000000000000" & "1111111101110111", "001111", '1'),
       (x"000000010000" & "1111111101110110", "100000", '1'),
       (x"000080000000" & "1111111001110111", "101111", '1'),
       (x"800000000000" & "1111111111111111", "111111", '1'),
       (x"000000000000" & "0000000000000000", "------", '0'));
  begin
    --  Check each pattern.
    for i in patterns'range loop
      --  Set the inputs.
      input <= patterns(i).input;
      --  Wait for the results.
      wait for 1 ns;
      --  Check the outputs.
      assert valid = patterns(i).valid
        report "valid signal wrong" severity error;
      if patterns(i).valid = '1' then
        assert index = patterns(i).index
          report "index wrong" severity error;
      end if;
    end loop;
    assert false report "end of test" severity note;
    --  Wait forever; this will finish the simulation.
    wait;
  end process;
end behav;

prio_encoder_16_4.vcd
$date
  Mon Feb 28 18:15:47 2022
$end
$version
  GHDL v0
$end
$timescale
  1 fs
$end
$scope module standard $end
$upscope $end
$scope module std_logic_1164 $end
$upscope $end
$scope module numeric_std $end
$upscope $end
$scope module prio_tb $end
$var reg 64 ! input[63:0] $end
$var reg 6 " index[5:0] $end
$var reg 1 # valid $end
$scope module prio_0 $end
$var reg 64 $ input[63:0] $end
$var reg 6 % index[5:0] $end
$var reg 1 & valid $end
$var reg 4 ' index0[3:0] $end
$var reg 4 ( index1[3:0] $end
$var reg 4 ) index2[3:0] $end
$var reg 4 * index3[3:0] $end
$var reg 1 + valid0 $end
$var reg 1 , valid1 $end
$var reg 1 - valid2 $end
$var reg 1 . valid3 $end
$scope module p_e_0 $end
$var reg 16 / input[15:0] $end
$var reg 4 0 index[3:0] $end
$var reg 1 1 valid $end
$upscope $end
$scope module p_e_1 $end
$var reg 16 2 input[15:0] $end
$var reg 4 3 index[3:0] $end
$var reg 1 4 valid $end
$upscope $end
$scope module p_e_2 $end
$var reg 16 5 input[15:0] $end
$var reg 4 6 index[3:0] $end
$var reg 1 7 valid $end
$upscope $end
$scope module p_e_3 $end
$var reg 16 8 input[15:0] $end
$var reg 4 9 index[3:0] $end
$var reg 1 : valid $end
$upscope $end
$upscope $end
$upscope $end
$enddefinitions $end
#0
b0000000000000000000000000000000000000000000000001000000000100000 !
b001111 "
1#
b0000000000000000000000000000000000000000000000001000000000100000 $
b001111 %
1&
b1111 '
bUUUU (
bUUUU )
bUUUU *
1+
0,
0-
0.
b1000000000100000 /
b1111 0
11
b0000000000000000 2
bUUUU 3
04
b0000000000000000 5
bUUUU 6
07
b0000000000000000 8
bUUUU 9
0:
#1000000
b0000000000000000000000000000000000000000000000000000000000000001 !
b000000 "
b0000000000000000000000000000000000000000000000000000000000000001 $
b000000 %
b0000 '
b0000000000000001 /
b0000 0
#2000000
b0000000000000000000000000000000000000000000000000010000000000000 !
b001101 "
b0000000000000000000000000000000000000000000000000010000000000000 $
b001101 %
b1101 '
b0010000000000000 /
b1101 0
#3000000
b0000000000000000000000000000000000000000000000001111111101110111 !
b001111 "
b0000000000000000000000000000000000000000000000001111111101110111 $
b001111 %
b1111 '
b1111111101110111 /
b1111 0
#4000000
b0000000000000000000000000000000100000000000000001111111101110110 !
b100000 "
b0000000000000000000000000000000100000000000000001111111101110110 $
b100000 %
b0000 )
1-
b1111111101110110 /
b0000000000000001 5
b0000 6
17
#5000000
b0000000000000000100000000000000000000000000000001111111001110111 !
b101111 "
b0000000000000000100000000000000000000000000000001111111001110111 $
b101111 %
b1111 )
b1111111001110111 /
b1000000000000000 5
b1111 6
#6000000
b1000000000000000000000000000000000000000000000001111111111111111 !
b111111 "
b1000000000000000000000000000000000000000000000001111111111111111 $
b111111 %
b1111 *
0-
1.
b1111111111111111 /
b0000000000000000 5
07
b1000000000000000 8
b1111 9
1:
#7000000
b0000000000000000000000000000000000000000000000000000000000000000 !
0#
b0000000000000000000000000000000000000000000000000000000000000000 $
0&
0+
0.
b0000000000000000 /
01
b0000000000000000 8
0:
